bda.plone.payment-2.0b1-py3.9-nspkg.pth
bda/plone/payment/__init__.py
bda/plone/payment/configure.zcml
bda/plone/payment/i18n.sh
bda/plone/payment/interfaces.py
bda/plone/payment/profiles.zcml
bda/plone/payment/setuphandlers.py
bda/plone/payment/upgrades.zcml
bda/plone/payment/cash/__init__.py
bda/plone/payment/cash/cash.pt
bda/plone/payment/cash/configure.zcml
bda/plone/payment/cash_in_advance/__init__.py
bda/plone/payment/cash_in_advance/cash_in_advance.pt
bda/plone/payment/cash_in_advance/configure.zcml
bda/plone/payment/cash_on_delivery/__init__.py
bda/plone/payment/cash_on_delivery/cash_on_delivery.pt
bda/plone/payment/cash_on_delivery/configure.zcml
bda/plone/payment/debit_order/__init__.py
bda/plone/payment/debit_order/configure.zcml
bda/plone/payment/debit_order/debit_order.pt
bda/plone/payment/invoice/__init__.py
bda/plone/payment/invoice/configure.zcml
bda/plone/payment/invoice/invoice.pt
bda/plone/payment/locales/bda.plone.payment.pot
bda/plone/payment/locales/manual.pot
bda/plone/payment/locales/de/LC_MESSAGES/bda.plone.payment.po
bda/plone/payment/locales/en/LC_MESSAGES/bda.plone.payment.po
bda/plone/payment/locales/fr/LC_MESSAGES/bda.plone.payment.po
bda/plone/payment/locales/it/LC_MESSAGES/bda.plone.payment.po
bda/plone/payment/locales/nl/LC_MESSAGES/bda.plone.payment.po
bda/plone/payment/locales/nn/LC_MESSAGES/bda.plone.payment.po
bda/plone/payment/locales/no/LC_MESSAGES/bda.plone.payment.po
bda/plone/payment/profiles/default/browserlayer.xml
bda/plone/payment/profiles/default/metadata.xml
bda/plone/payment/profiles/default/registry.xml
bda/plone/payment/profiles/uninstalll/browserlayer.xml
bda/plone/payment/profiles/uninstalll/registry.xml
bda/plone/payment/resources/payment.css
bda/plone/payment/resources/payment.css.map
bda/plone/payment/resources/payment.min.css
bda/plone/payment/six_payment/__init__.py
bda/plone/payment/six_payment/aborted.pt
bda/plone/payment/six_payment/configure.zcml
bda/plone/payment/six_payment/failed.pt
bda.plone.payment-2.0b1.dist-info/LICENSE.rst
bda.plone.payment-2.0b1.dist-info/LICENSE_GPL.rst
bda.plone.payment-2.0b1.dist-info/METADATA
bda.plone.payment-2.0b1.dist-info/WHEEL
bda.plone.payment-2.0b1.dist-info/namespace_packages.txt
bda.plone.payment-2.0b1.dist-info/top_level.txt
bda.plone.payment-2.0b1.dist-info/RECORD
